opsanyctl
tests
